urturn/REQUIREMENTS
urturn/VERSION
urturn/__init__.py
urturn/job.py
urturn/scheduler.py
urturn/trigger.py
urturn/webapp.py
urturn/templates/adapted.min.css
urturn/templates/details.css
urturn/templates/index.html
urturn/templates/job_config.html
urturn-0.1.6.dist-info/LICENSE
urturn-0.1.6.dist-info/METADATA
urturn-0.1.6.dist-info/WHEEL
urturn-0.1.6.dist-info/top_level.txt
urturn-0.1.6.dist-info/RECORD
