Metadata-Version: 2.1
Name: urturn
Version: 0.1.6
Summary: Analyse git repositories
Home-page: https://github.com/MatthiasRieck/urturn
Author: Matthias Rieck
Author-email: Matthias.Rieck@tum.de
License-File: LICENSE
Requires-Dist: flask
Requires-Dist: flask-socketio
